setup.py
korbit/__init__.py
korbit/private_api.py
korbit/public_api.py
korbit_api.egg-info/PKG-INFO
korbit_api.egg-info/SOURCES.txt
korbit_api.egg-info/dependency_links.txt
korbit_api.egg-info/requires.txt
korbit_api.egg-info/top_level.txt