Metadata-Version: 1.1
Name: korbit-api
Version: 0.1.0
Summary: korbit API wrapper for Python
Home-page: http://github.com/Hoonjin/korbit-python/
Author: Daniel Ji
Author-email: bwjhj1030@gmail.com
License: MIT
Platform: UNKNOWN
Classifier: Programming Language :: Python
Classifier: Programming Language :: Python :: 3
Classifier: License :: OSI Approved :: MIT License
Classifier: Operating System :: OS Independent
Classifier: Topic :: Software Development :: Libraries :: Python Modules
